.coveragerc
.dictionary
.pyspelling.yml
LICENSE.md
MANIFEST.in
README.md
changelog.md
pyproject.toml
setup.cfg
setup.py
tox.ini
docurial_extensions.egg-info/PKG-INFO
docurial_extensions.egg-info/SOURCES.txt
docurial_extensions.egg-info/dependency_links.txt
docurial_extensions.egg-info/top_level.txt
materialx/__init__.py
materialx/__meta__.py
materialx/emoji.py
requirements/docs.txt
requirements/lint.txt
requirements/project.txt
requirements/test.txt